eider.py
eider-2.0.1.dist-info/LICENSE
eider-2.0.1.dist-info/METADATA
eider-2.0.1.dist-info/WHEEL
eider-2.0.1.dist-info/top_level.txt
eider-2.0.1.dist-info/RECORD
